{
   "id_query": "796039",
   "total": 34168,
   "total_current": 100,
   "max_score": 70.3944,
   "origin_question": "Cho em hỏi màn hình laptop của em bị chia làm 4 phần, có cách nào để màn hình trở lại bình thường được không ạ. Em cám ơn!",
   "hits": [
      {
         "score": 34.458443,
         "id": "1163560",
         "field_search": "question",
         "question": "Laptop của em lúc mới mở máy thì card màn hình rời vẫn nhận driver bình thường nhưng sau khi em sự dụng được tầm 30p thì card màn hình rời không nhận driver nữa . Anh chị cho em xin cách khác phục ạ. Xin cám ơn!!",
         "answer": "_",
         "relate_q_q": 0
      },
      {
         "score": 34.0067,
         "id": "855174",
         "field_search": "question",
         "question": "Laptop hiệu dell của em sao màn hình hiển thị màu xanh không thể làm gì được cả chỉ thấy con chuột thôi giúp em làm sao cho nó trở lại bình thường với ad?",
         "answer": "_",
         "relate_q_q": 0
      },
      {
         "score": 33.501114,
         "id": "1166045",
         "field_search": "question",
         "question": "Xin chào ạ!  cho em hỏi làm thế nào để chia màn hình trên vivoY91C ạ",
         "answer": "_",
         "relate_q_q": 0
      },
      {
         "score": 32.20169,
         "id": "838800",
         "field_search": "question",
         "question": "Cho em hỏi iPhone 4 của em vào Facebook hay bị chậm và xem youtube thì xem bình thường mà nó bị đứng màn hình vậy là cần phải chạy lại phần mềm đúng không ad",
         "answer": "_",
         "relate_q_q": 0
      },
      {
         "score": 31.66457,
         "id": "1008397",
         "field_search": "question",
         "question": "Cho em hỏi. Galaxy A5 2015 của em bị nhấp nháy màn hình liên tục khi để chế độ sáng thấp nhất, để độ sáng cao hơn thì không thấy nháy. Màn hình cảm ứng vẫn bình thường. E đã cài đặt lại máy mà vẫn vậy. Đó có phải do lỗi phần cứng không. Có phải thay mới màn hình không ạ",
         "answer": "_",
         "relate_q_q": 0
      },
      {
         "score": 31.650862,
         "id": "1013312",
         "field_search": "question",
         "question": "Em dùng điện thoại oppo neo 9 trong một lần thay đổi chủ đề e bị kẹt màn hình khoá.. Bây h dù có thay đổi chủ đề khác rồi vẫn không thể thay đổi màn hình khoá.. Em Phải làm thế nào để màn hình khoá trở về như mặc định ạ.. Em cám ơn a/c",
         "answer": "_",
         "relate_q_q": 0
      },
      {
         "score": 31.502174,
         "id": "1009046",
         "field_search": "question",
         "question": "Điện thoại iphone 5 của em cứ tự xoay màn hình. Reset  thì bình thường trở lại nhưng một lúc sau lại bị lại.",
         "answer": "_",
         "relate_q_q": 0
      },
      {
         "score": 31.006943,
         "id": "888061",
         "field_search": "question",
         "question": "  kết nối được mà nó không hiển thị kên màn hình chị e hỏi làm cách nào để nó lại đc bình thường ",
         "answer": "_",
         "relate_q_q": 0
      },
      {
         "score": 30.720142,
         "id": "1144367",
         "field_search": "question",
         "question": "ipad của mình vừa bị đổ nước vào nút bật máy và máy bị chập chờn, đang chơi game mà cứ bị out ra màn hình khóa hoặc tự bật nút tắt nguồn, bây giờ thì màn hình cứ sáng lên và có hình quả táo, làm cách nào để máy trở lại bình thường?",
         "answer": "_",
         "relate_q_q": 0
      },
      {
         "score": 30.488771,
         "id": "1005970",
         "field_search": "question",
         "question": "Ad cho em hỏi em đang dùng máy samsung j5 prime nhưng tự dưng máy xuất hiện vết đỏ ở 4 góc màn hình, để một thời gian thì lại không thấy nữa hiện tượng này là máy bị làm sao và cách khắc phục như thế nào ạ. Em cám ơn",
         "answer": "_",
         "relate_q_q": 0
      },
      {
         "score": 30.293512,
         "id": "855851",
         "field_search": "question",
         "question": " cho e hỏi....e bị mất ip5s làm cách nào để không để người ta bẻ khoá màn hình của em và tìm lại điện thoại ạ? ",
         "answer": "_",
         "relate_q_q": 0
      },
      {
         "score": 30.045588,
         "id": "1137817",
         "field_search": "question",
         "question": "Dạ cho em hỏi là đt s8 của em hôm nay có triệu chứng là bị xanh màn hình sọc sọc và đơ màn hình em khởi đôgj lại thì bình thường sau 1 hồi lại bị tiếp đt em bị gì v ạ",
         "answer": "_",
         "relate_q_q": 0
      },
      {
         "score": 29.974787,
         "id": "882896",
         "field_search": "question",
         "question": " QTV cho em hỏi laptop của em bị lỗi nhòe màn hình AOE , cách khắc phục thế nào ạ? ",
         "answer": "_",
         "relate_q_q": 0
      },
      {
         "score": 29.838411,
         "id": "1135469",
         "field_search": "question",
         "question": "Các bác dùng xiaomi mi 8 lite cho em hỏi: chơi pubg màn hình bị tràn ra phần tai thỏ, rất khó chơi, làm cách nào để khắc phục ạ? em cảm ơn",
         "answer": "_",
         "relate_q_q": 0
      },
      {
         "score": 29.799217,
         "id": "1165845",
         "field_search": "question",
         "question": "Em mới mua con ss a50 và giờ nó bị bể kính màn hình. Thì có đem tới tgdd làm lại dc không ? Cho em hỏi giá luôn ạ . Em cám ơn !",
         "answer": "_",
         "relate_q_q": 0
      },
      {
         "score": 29.745743,
         "id": "782344",
         "field_search": "question",
         "question": "Iphone 4S của em em mới cài đặt Asphalt vào, ( trước vẫn chạy như trâu và chắc chắn vẫn chạy được) rồi bị đơ một lúc do em bật nhiều chương trình quá, sau đó em tắt màn hình rồi bật lại nhập mật khẩu bình thường thì thấy máy treo, như bình thường vẫn làm em lại tắ màn hình để nhập lại tuy nhiên máy không hiện lên gì nữa, cắm vào máy tính vẫn hiện bình thường như thế này là xung đột phần mềm đúng không ạ, em cần phải làm gì để thoát khỏi tình trạng này, em cảm ơn.",
         "answer": "_",
         "relate_q_q": 0
      },
      {
         "score": 29.650333,
         "id": "788037",
         "field_search": "question",
         "question": "QTV cho em hỏi giấy bảo hành miến dán màn hình laptop của em bị mờ chữ hết giờ em muốn đi dán lại màn hình phải làm như thế nào",
         "answer": "_",
         "relate_q_q": 0
      },
      {
         "score": 29.491055,
         "id": "866446",
         "field_search": "question",
         "question": "Em có 1 cái iPhone 4s tự nhiên nó bị liệt mất phần trên + phần dưới của màn hình tầm 0.5cm có cách nào để khắc phục không ạ",
         "answer": "_",
         "relate_q_q": 0
      },
      {
         "score": 29.41181,
         "id": "1135855",
         "field_search": "question",
         "question": "Nokia 5 của mình bị vỡ màn hình, vẫn sử dụng cảm ứng bình thường. máy mình mua từ tháng 9 năm 2017. Cho mình hỏi bên thế giới di động có hỗ trợ thay màn hình không? Giá thế nào? Cám ơn...",
         "answer": "_",
         "relate_q_q": 0
      },
      {
         "score": 29.406612,
         "id": "758541",
         "field_search": "question",
         "question": "QTV cho em hỏi iPhone 4 của em bị treo máy, màn hình tắt tối thui, mở nguồn cũng không lên, nút Home bị hư rồi, giờ làm cách nào cho máy mở lên được ạ? Ở TGDD có sửa không?",
         "answer": "_",
         "relate_q_q": 0
      },
      {
         "score": 29.13175,
         "id": "796301",
         "field_search": "question",
         "question": "Cho em hỏi em dùng iphone 5C lúc để màn hình sáng ít thì cảm ứng không sao nhưng bật sáng nhiều thì cảm ứng lại đơ,tắt màn hình xong bật...cảm ứng lại bình thường nhưng chỉ được 15 20s là lại lặp lại cảm ứng như thế.!!!Vậy cho e hỏi máy bị làm sao ạ...?",
         "answer": "_",
         "relate_q_q": 0
      },
      {
         "score": 29.081495,
         "id": "795219",
         "field_search": "question",
         "question": "Cho em hỏi ạ, màn cảm ứng máy iphone 4s có nằm cả phần rìa không ạ hay chỉ mỗi phần màn hình sáng thôi ạ, em bị vỡ nát gần phím lúc màn hình sáng nhìn qua khe nứt có ánh sáng vậy có phải hỏng cả cảm ưng không ạ và thay bây giờ khoảng bao nhiêu ạ. Em cám ơn !",
         "answer": "_",
         "relate_q_q": 0
      },
      {
         "score": 29.0727,
         "id": "928827",
         "field_search": "question",
         "question": "  Cho em hỏi iphone 4 hiện giao diện tớ làm cách nào để cho về bình thường ạ  ",
         "answer": "_",
         "relate_q_q": 0
      },
      {
         "score": 28.979631,
         "id": "828315",
         "field_search": "question",
         "question": "iPhone 5 của em bị khóa màn hình nó yêu cầu kế nối với itunescho em hỏi làm cách nào để mở khóa màn hình khi em chỉ có máy tính asus và dây cáp",
         "answer": "_",
         "relate_q_q": 0
      },
      {
         "score": 28.800339,
         "id": "1164862",
         "field_search": "question",
         "question": "em mới mua điện thoại samsung m20 được 1 tháng. em bất cẩn làm rớt điện thoại. và bể màn hình. em muốn hỏi có màn hình mới để thay cho máy ko ad??? nếu có thì giá bao nhiêuem cám ơn",
         "answer": "_",
         "relate_q_q": 0
      },
      {
         "score": 28.765453,
         "id": "1134662",
         "field_search": "question",
         "question": "Hiện em đang dùng laptop ASUS X555U, gần đây màn hình máy tính của em thường xuyên xuất hiện tình trạng bị nhiễu, chập chờn. Cho em hỏi máy bị làm sao và cách giải quyết như thế nào ạ",
         "answer": "_",
         "relate_q_q": 0
      },
      {
         "score": 28.661884,
         "id": "1147395",
         "field_search": "question",
         "question": "Em đang dùng s6 edge plus nhưng khi chỉnh màn hình lên 2k thì màn hình vào game hoặc ứng dụng bị thu bé lại Camera của em vẫn dùng bình thường nhung6em không thể quây phim chậm được vì sao vậy ạ Cảm ơn ad",
         "answer": "_",
         "relate_q_q": 0
      },
      {
         "score": 28.607882,
         "id": "758542",
         "field_search": "question",
         "question": "QTV cho em hỏi iPhone 4 của em bị treo máy, màn hình tắt tối thui, mở nguồn lên cũng không lên, nút Home thì bị hư rồi, giờ làm cách nào cho máy mở lên được ạ? Ở TGDD có sửa không?",
         "answer": "_",
         "relate_q_q": 0
      },
      {
         "score": 28.571419,
         "id": "812149",
         "field_search": "question",
         "question": "Anh chị cho em hỏi em có con iphone 4 thường bị khoá màn hình do em mở sai nhiều lần không biết có bẻ khóa được không ạ?ếóế",
         "answer": "_",
         "relate_q_q": 0
      },
      {
         "score": 28.546146,
         "id": "768747",
         "field_search": "question",
         "question": "Chào anh chị ! en có 1 iPad air 2 . trong quá trình sử dụng em lỡ làm mất mật khẩu màn hình khóa.- iCoud của em cũng quên mất .- có cách nào mở giùm em không ạ ? - em xin cám ơn ",
         "answer": "_",
         "relate_q_q": 0
      },
      {
         "score": 28.32784,
         "id": "761444",
         "field_search": "question",
         "question": "Dạ em đang dùng iPhone 4S, cách đây khoảng 1 tháng, điện thoại của em có bị thấm nước và em đã đem đi sửa, khi về em dùng đt bình thường, nhưng đt của em không biết sao, màn hình cứ tối đen không lên mấy lần, em có gọi thử thì vẫn gọi được nhưng màn hình đt vẫn tối đen, không lên được. Em phải đợi khi đt hết pin, cắm sạc thì mới có thể sử dụng lại được. Cho em hỏi là đt của em bị gì và sửa chữa như thế nào ạ? Em xin cảm ơn.",
         "answer": "_",
         "relate_q_q": 0
      },
      {
         "score": 28.294865,
         "id": "1137115",
         "field_search": "question",
         "question": "AD ơi cho em hỏi đt của em bị rớt bể màn hình, cảm ứng vẫn xài bình thường, chỉ hơi bị lem và khi mở máy thì hơi chớp. em phải làm tehes nào ạ, đt của em là s8",
         "answer": "_",
         "relate_q_q": 0
      },
      {
         "score": 28.251913,
         "id": "758513",
         "field_search": "question",
         "question": "Cho em hỏi iPhone 4 của em bị treo máy, màn hình tắt tối thui, mở nguồn cũng không lên, nút home thì bị hư rồi, giờ làm cách nào cho máy mở lên được à? Ở tgdd có sửa được không?",
         "answer": "_",
         "relate_q_q": 0
      },
      {
         "score": 28.223654,
         "id": "761434",
         "field_search": "question",
         "question": "Laptop của em lâu lâu hay bị lỗi not responding, có khi bị khi mới khởi động máy, có khi đang xài bình thường thì bị, cho hỏi máy em bị lỗi gì, làm sao để khắc phục, xin cám ơn.",
         "answer": "_",
         "relate_q_q": 0
      },
      {
         "score": 28.111332,
         "id": "1152584",
         "field_search": "question",
         "question": "Cho em hỏi là em mới mua Nokia 8.1 sao chia đôi màn hình lại không được ạ?nó báo lỗi như dưới ảnh ạ ",
         "answer": "_",
         "relate_q_q": 0
      },
      {
         "score": 27.95709,
         "id": "780011",
         "field_search": "question",
         "question": "Cho em hỏi..em dùng iphone 4s, lúc em tắt nguồn và mở lên lại thì màn hình của em không lướt để mở khóa được vậy là sao, những nút home vẫn hoạt động bình thường nhờ tgdd trả lời dùm em.em cảm ơn!",
         "answer": "_",
         "relate_q_q": 0
      },
      {
         "score": 27.84298,
         "id": "772302",
         "field_search": "question",
         "question": "Cho em hỏi là iPhone 5C của em tự nhiên bị đóng băng cảm ứng nhưng tắt màn hình đi rồi bật lại thì cảm ứng lại bình thường, một lúc sau nó lại tiếp diễn, vậy cho em hỏi máy bị làm sao ạ??",
         "answer": "_",
         "relate_q_q": 0
      },
      {
         "score": 27.822166,
         "id": "1024322",
         "field_search": "question",
         "question": "Em dùng samsung galaxy j5. Khi chiều em có bị đổ nước gần đt. Nhưng k bị dính đt nhiều. Hiện tại thì nếu em khóa màn hình thì không khóa được màn hình vẫn sáng ngay màn hình khóa. Hoặc tắt ròi thì lát lại sáng lên. Có khi đang xài thì lại tắt tối và lại sáng trở lại. Cho em hỏi là đt em đang gặp vấn đề thế nào ạ?",
         "answer": "_",
         "relate_q_q": 0
      },
      {
         "score": 27.813362,
         "id": "790430",
         "field_search": "question",
         "question": "Ad cho em hỏi máy iphone 5 của em mở khoá màn hình xong bị đơ cảm ứng rồi em khoá lại mở lên vẫn bình thường tại sao lại như vậy ạ có phải mang đi sửa không ạ?",
         "answer": "_",
         "relate_q_q": 0
      },
      {
         "score": 27.729649,
         "id": "781108",
         "field_search": "question",
         "question": "Laptop dell của em đang cài win 8.1 có cạc màn hình 2gb, em có cài NVIDIA GeForce Experience mà sao không thể update driver được, mỗi lần download driver mới là không được, cho hỏi bị lỗi gì vậy, xin cám ơn",
         "answer": "_",
         "relate_q_q": 0
      },
      {
         "score": 27.696709,
         "id": "1001688",
         "field_search": "question",
         "question": "cho em hỏi khi em quay slow motion trên sony xzs thì màn hình bị chớp nháy , nhưng khi chuyển qua quay video bình thường thì không có chuyện gì xảy ra. cho em hỏi cách khắc phục với ạ. Em cảm ơn ad",
         "answer": "_",
         "relate_q_q": 0
      },
      {
         "score": 27.67487,
         "id": "884906",
         "field_search": "question",
         "question": "cách đây 1 tuần em có nhặt được 1 chiếc ip5s. nhưng không thấy chủ của chiếc ip liên lạc hay đến tìm để lấy lại máy, nên giờ em muốn gỡ khóa màn hình vs tk icloud để sử dụng liệu có được không. em xin cám ơn !",
         "answer": "_",
         "relate_q_q": 0
      },
      {
         "score": 27.618149,
         "id": "996186",
         "field_search": "question",
         "question": "cho em hỏi..màn hình oppo a37 của em bi mẻ góc nhỏ..nhung hơn 6 tháng rui xài bình thường..nhug gio tự nhiên màn hình rát kho bấm và nok tự đong nhay luôn...z là do man hình hay phần mềm ak..va chỉ em cách khac phục voi..",
         "answer": "_",
         "relate_q_q": 0
      },
      {
         "score": 27.423414,
         "id": "1156142",
         "field_search": "question",
         "question": "Chào mấy anh chị, em xài Samsung J7+ bị rơi vỡ màn hình và màn hình bị sọc trắng che mất 1 phần. Em có thể đem ra cho bên mình gửi về hãng sửa được không ạ. Cho em hỏi luôn chi phí nếu sửa được ạ. Em cảm ơn.",
         "answer": "_",
         "relate_q_q": 0
      },
      {
         "score": 27.371878,
         "id": "1160123",
         "field_search": "question",
         "question": "Màn hình oppo A37 của em bị bể nát màn hình có thay Được không ạ",
         "answer": "_",
         "relate_q_q": 0
      },
      {
         "score": 27.301647,
         "id": "772833",
         "field_search": "question",
         "question": " Em muốn máy em có nút trở lại trên màn hình để thoát khỏi dễ dàng hơn của điện thoại iPhone? ",
         "answer": "_",
         "relate_q_q": 0
      },
      {
         "score": 27.294266,
         "id": "1143890",
         "field_search": "question",
         "question": "cho em hỏi ạ làm thế nào để cho biểu tượng gaem fi4 ra màn hình destop vậ ạlàm ơn giúp em với ạ >>>>................................................................................................",
         "answer": "_",
         "relate_q_q": 0
      },
      {
         "score": 27.291193,
         "id": "1003566",
         "field_search": "question",
         "question": "Cho em hỏi điện thoại của em mới mua được gần 3 tháng và bị bể màn hình cho em hỏi chính sách bảo hành của TGDD có bảo hành và thay màn hình miễn phí không vậy ạ ? Em cảm ơn .",
         "answer": "_",
         "relate_q_q": 0
      },
      {
         "score": 27.234499,
         "id": "1015275",
         "field_search": "question",
         "question": "Ad giúp em gấp với ,, điện thoại mobiistar b247 màn hình bị chia đôi ,,, làm sao em khắc phục ạ",
         "answer": "_",
         "relate_q_q": 0
      },
      {
         "score": 27.052437,
         "id": "991815",
         "field_search": "question",
         "question": "Năm ngoái  tôi có mua laptop Lenovo ở TGDD, giờ vừa mới hết bảo hành.Nay màn hình laptop bị lỏng, hình không cử động. nếu tôi ấn nhẹ vào màn hình thì màn hình làm việc bình thường, buông tay ra thì hình bị đứng.Cho hỏi có thể sửa laptop cho tôi vấn đề này mà không tính phí ?",
         "answer": "_",
         "relate_q_q": 0
      },
      {
         "score": 27.03987,
         "id": "999915",
         "field_search": "question",
         "question": "cho e hỏi mình có thay màn hình laptop ko ạ? nếu có thì màn hình 15.6 inch có giả khoảng bao nhiêu. e cám ơn ạ",
         "answer": "_",
         "relate_q_q": 0
      },
      {
         "score": 26.986748,
         "id": "1016855",
         "field_search": "question",
         "question": "Xin cho em hỏi thay kính màn hình samsung j7 pro giá bao nhiêu vậy ạ? Em cám ơn!",
         "answer": "_",
         "relate_q_q": 0
      },
      {
         "score": 26.954906,
         "id": "766787",
         "field_search": "question",
         "question": "Cho em hỏi máy em là iphone 5s , đang dùng thì màn hình bị đơ kiểu lướt fb không được, sau đó em có khoá màn hình, mở lại thì màn hình không lên, nhưng gọi vào thì điện vẫn rung , nhưng màn hình vẫn tối thui em phải làm sao đây ạ ? ",
         "answer": "_",
         "relate_q_q": 0
      },
      {
         "score": 26.914957,
         "id": "847290",
         "field_search": "question",
         "question": " Ad cho em hỏi lớp phủ màn hình là gì ạ và làm sao đẻ tắt nó vì em cứ bị nó hiện lên hoài . cám ơn ad ạ   ",
         "answer": "_",
         "relate_q_q": 0
      },
      {
         "score": 26.868895,
         "id": "1137336",
         "field_search": "question",
         "question": "Anh/chị cho em hỏi: em dùng 5s, bây giờ bị loạn cảm cứng + màn hình 2 màu. Nhưng vẫn sử dụng bình thường, lâu lâu bấm cảm ứng nó không ăn thôi. Cho em hỏi là có cách nào khắc phục không ạ??",
         "answer": "_",
         "relate_q_q": 0
      },
      {
         "score": 26.777607,
         "id": "827542",
         "field_search": "question",
         "question": " cho e hỏi tại sao máy tính của e vào phần downloads không được vào nó lại trở ra màn hình chính ",
         "answer": "_",
         "relate_q_q": 0
      },
      {
         "score": 26.769201,
         "id": "991387",
         "field_search": "question",
         "question": "cho em hỏi là iphone 4 không nghe được nhạc hay vào youtobe xem không nghe được tiếng nhưng chuông gọi đến vẫn đổ và kêu bình thường thì bị lỗi gì và cách khác phục em cám ơn",
         "answer": "_",
         "relate_q_q": 0
      },
      {
         "score": 26.704048,
         "id": "1136557",
         "field_search": "question",
         "question": "Dạ chào anh (chị).. Em đang xài laptop Lenovo Yoga 520 mới mua khoảng hơn 6 tháng tại thế giới di động.. Máy có màn hình cảm ứng mà em ít xài cảm ứng trên màn hình.. Đến hôm nay e chạm vào màn hình thì mới phát hiện đã bị vô hiệu hóa.. Em cũng không biết bị từ khi nào.. Lên mạng search thì có chỉ cách bật/tắt màn hình cảm ứng là Disable HDI compliant touch screen.. Em làm trên máy thì không có HDI complint touch screen.. Giờ em phải làm sao để sử dụng màn hình cảm ứng đây ạ! Em cảm ơn!",
         "answer": "_",
         "relate_q_q": 0
      },
      {
         "score": 26.676495,
         "id": "995945",
         "field_search": "question",
         "question": "em có 1 chiếc iphone 6s không hiểu sao e khôi phục lại thì bị treo iphone ở màn hình. báo kết nối với itune dù khôi phục lại nhiều lần cũng không được.máy cũng không lên màn hình sử dụng như bình thường nhờ anh chị giup em với em cảm ơn ạ",
         "answer": "_",
         "relate_q_q": 0
      },
      {
         "score": 26.669388,
         "id": "767176",
         "field_search": "question",
         "question": " cho em hỏi bật nguồn laptop nhưng màn hình không sáng mà máy vẫn hoạt động là sao ạ? làm sao để bật màn hình lên ạ? ",
         "answer": "_",
         "relate_q_q": 0
      },
      {
         "score": 26.58313,
         "id": "999671",
         "field_search": "question",
         "question": "Lenovo vipe p1 bị bể màn hình, cảm ứng vẫn dùng bình thường. Cho hỏi thay màn hình thay bao nhiêu tiền? Và màn hình có như gôca của điện thoại không??",
         "answer": "_",
         "relate_q_q": 0
      },
      {
         "score": 26.565489,
         "id": "1003333",
         "field_search": "question",
         "question": "Đt em iPhone 5 thường bị vô nước màn hình không biết có cách nào sửa được mà không cần tháo iPhone không ạMong ad trả lời giúp emXin cảm ơn",
         "answer": "_",
         "relate_q_q": 0
      },
      {
         "score": 26.495752,
         "id": "755257",
         "field_search": "question",
         "question": "Em sài iPhone 5 sài vẫn bình thường em không làm rớt, hay va chạm mạnh gì cả. Sài bấm bình thường một lúc sau nó đơ màn hình cảm ứng không  bấm được nữa em tắt nguồn và khỏi động lại thì sài được một chút và tới bây giờ nó hay bị loạn cảm ứng đôi lúc đang sài nó lại nhảy lung tung và kéo không đi :< .=\"\" cho=\"\" em=\"\" biết=\"\" em=\"\" phải=\"\" làm=\"\" sao,=\"\" em=\"\" cám=\"\">",
         "answer": "_",
         "relate_q_q": 0
      },
      {
         "score": 26.472467,
         "id": "786257",
         "field_search": "question",
         "question": "Chào, em đang xài iPhone 6 dạo gần đây máy của em đang xài bỗng dưng bị đứng màn hình sau đó hiện màn hình màu xanh rồi tự động tắt nguồn, em khởi động lại xài bình thường và sau đó lại bị lỗi như vậy? Không biết như thế nào?",
         "answer": "_",
         "relate_q_q": 0
      },
      {
         "score": 26.454887,
         "id": "988480",
         "field_search": "question",
         "question": "cho em hỏi laptop của em mua ở tgdd nay bị hở sáng màn hình vậy có đuọc bảo hành không ạ",
         "answer": "_",
         "relate_q_q": 0
      },
      {
         "score": 26.415993,
         "id": "1164386",
         "field_search": "question",
         "question": "Ad ơi cho em hỏi ! Em vừa mua 1 máy samsung galaxy A50, máy ảnh của máy chỉ chụp được chế độ âm bản, không chụp được chế độ bình thường ? Vậy em phải làm như thế nào mới có thể điều chỉnh lại ạ ?? Xin cám ơn ạ",
         "answer": "_",
         "relate_q_q": 0
      },
      {
         "score": 26.396162,
         "id": "999337",
         "field_search": "question",
         "question": "cho em hỏi  cách chụp màn hình nokia 3 làm thế nào     ",
         "answer": "_",
         "relate_q_q": 0
      },
      {
         "score": 26.389677,
         "id": "1168191",
         "field_search": "question",
         "question": "Cho em hỏi đt samsung A30 chụp màn hình không được vì chính sách bảo mật thì làm cách nào ạ",
         "answer": "_",
         "relate_q_q": 0
      },
      {
         "score": 26.378935,
         "id": "1155028",
         "field_search": "question",
         "question": "dạ cho em hỏi, làm thế nào để sửa iphone 4 khi xuát hiện 1 nửa là hình nền, 1 nửa là hình của notification center ạ. Em cảm ơn.",
         "answer": "_",
         "relate_q_q": 0
      },
      {
         "score": 26.354532,
         "id": "832779",
         "field_search": "question",
         "question": " Khi bật máy tính bàn, màn hình HP hiện lỗi MONITOR GOING TO SLEEP, cho em hỏi cách khắc phục ạ. E cám ơn. ",
         "answer": "_",
         "relate_q_q": 0
      },
      {
         "score": 26.297497,
         "id": "761142",
         "field_search": "question",
         "question": "Anh chị ơi cho em hỏi iPhone 4S của em đang chạy Instagram  thì bỗng dưng bị treo lại, không thể ấn phím Home, khóa màn hình thì nó ko lên màn hình nhập passcode mà vẫn giữ nguyên ứng dụng Instagram. Gọi thử vào cũng không lên nổi. Như thế là bị làm sao vậy ạ và có cách gì sửa được không?Em cảm ơn!",
         "answer": "_",
         "relate_q_q": 0
      },
      {
         "score": 26.242939,
         "id": "1157964",
         "field_search": "question",
         "question": "Cho em hỏi ĐT hưawei nova i3 làm sao để biết màn hình còn zin kh ạTại em mua lại của 1 ng khác em thấy viền màn hình hơi hở 1 số chỗ và có đính kéo như đã thấy màn hình rồi ấy ạ",
         "answer": "_",
         "relate_q_q": 0
      },
      {
         "score": 26.2154,
         "id": "766896",
         "field_search": "question",
         "question": "thegioididong cho em hỏi laptop của em mua lại thegioididong em muốn cài lại win thì có tính phí không ạ laptop em hiệu ASUS sao chụp màn hình trong game liên minh huyền thoại không được ạ.",
         "answer": "_",
         "relate_q_q": 0
      },
      {
         "score": 26.207195,
         "id": "1019724",
         "field_search": "question",
         "question": "QTV chỉ dùm, làm sao tắt lớp phủ màn hình cho Sony C 4 vậy....cám ơn",
         "answer": "_",
         "relate_q_q": 0
      },
      {
         "score": 26.131487,
         "id": "777021",
         "field_search": "question",
         "question": " Cho em hỏi iPhone 5 bị hở màn hình có sửa lại được không? ",
         "answer": "_",
         "relate_q_q": 0
      },
      {
         "score": 26.124866,
         "id": "998234",
         "field_search": "question",
         "question": "Ad oi, cho em hỏi, điện thoại của em bị nứt góc trái bên dưới. Em có thể dán lại màn hình được không ạ? Chỉ dán mà ko thay màn hình mới có ảnh hưởng gì đến cảm ứng không ạ?",
         "answer": "_",
         "relate_q_q": 0
      },
      {
         "score": 26.090736,
         "id": "780138",
         "field_search": "question",
         "question": "cho em hỏi em xài laptop sony vaio e dang on may bình thường xong khi e mở 1 chương trình thì đột nhiên màn hình bị sọc rô xong tắt đen luôn nhưng máy vẫn hoạt động bình thường vậy cho e hỏi máy em bị gì ạ? :'(",
         "answer": "_",
         "relate_q_q": 0
      },
      {
         "score": 26.077953,
         "id": "795436",
         "field_search": "question",
         "question": " Cho em hỏi sao laptop của em bấm vào nút start ở góc trái màn hình sao không được ạ ",
         "answer": "_",
         "relate_q_q": 0
      },
      {
         "score": 26.050686,
         "id": "1145593",
         "field_search": "question",
         "question": "Em đang sử dụng Xiaomi Redmi Note 4 Sao đt của em lại không có chế độ xoay màn hình ạ ? Chơi game hay coi phim gì cũng không thể xoay được ạ !! Có cách nào khắc phục không ạ ?",
         "answer": "_",
         "relate_q_q": 0
      },
      {
         "score": 26.025105,
         "id": "1003933",
         "field_search": "question",
         "question": "Dt của  lenovo A6020a40 bị bể màn hinh cho em hỏi gia của màn hình la bao nhiu em cảm ơn",
         "answer": "_",
         "relate_q_q": 0
      },
      {
         "score": 26.01611,
         "id": "1167773",
         "field_search": "question",
         "question": "Vấn đề 1: Iphone 6 của em bỗng nhiên bị mất chế độ rung. Em không thể nhận được thông báo rung của tin nhắn hay cuộc gọi tới. Em đã thử lên mạng tìm nhiều cách giải quyết và làm thử nhiều lần nhưng không được. Vấn đề 2: em đặt báo thức nhiều cái và nó lặp lại nhiều lần, bình thường em bấm nút nguồn hay màn hình để dừng lại thì được nhưng vài hôm nay bấm nút nguồn hay màn hình để dừng lại thì không được và bị đứng máy. Điện thoại em mua ở tgdđ từ năm 2017 ạ",
         "answer": "_",
         "relate_q_q": 0
      },
      {
         "score": 25.996029,
         "id": "1150288",
         "field_search": "question",
         "question": "Điện thoại ss j6 của em dán miếng cường lực full màn hình thì hay bị đơ màn hình, cụ thể là thỉnh thoảng sau khi gọi điện cho người khác xong thì jieenj tượng này xuất hiện và phải tắt màn hình đi mở lại thì máy lại bình thường. Cho em hỏi đây là do miếng dán hay do máy bị lỗi cảm ứng ạ ?",
         "answer": "_",
         "relate_q_q": 0
      },
      {
         "score": 25.96189,
         "id": "780718",
         "field_search": "question",
         "question": " mình bị khóa màn hình Galaxy Note 5, làm cách nào có thể mở lại màn hình ",
         "answer": "_",
         "relate_q_q": 0
      },
      {
         "score": 25.950365,
         "id": "1139322",
         "field_search": "question",
         "question": "cho em hỏi có cách nào khắc phục bị ngắt wifi và 4g khi tắt màn hình oppo a3s không ạ..cứ tắt màn hình là tự ngắt mạng ạ",
         "answer": "_",
         "relate_q_q": 0
      },
      {
         "score": 25.915989,
         "id": "864137",
         "field_search": "question",
         "question": " Làm sao để trở về màn hình dạng icon ban đầu. chỉ cách trở về giùm cái  ",
         "answer": "_",
         "relate_q_q": 0
      },
      {
         "score": 25.879414,
         "id": "1164943",
         "field_search": "question",
         "question": "Điện thoại J4 của mình trước khi cập nhật thì vẫn chia đc màn hình nhưng cập nhật xong lại không chia màn hình đc",
         "answer": "_",
         "relate_q_q": 0
      },
      {
         "score": 25.879244,
         "id": "1011512",
         "field_search": "question",
         "question": "cho em hỏi có laptop nào tầm giá dưới 17tr màn hình 15 chơi được dota2 max setting không ạ",
         "answer": "_",
         "relate_q_q": 0
      },
      {
         "score": 25.861084,
         "id": "1010341",
         "field_search": "question",
         "question": "Anh/Chị cho em hỏi điện thoại samsung galaxy E5 bị cấn bể ở góc đt (gần nút trở về) hiện bị tắt màn hình. cảm ứng vẫn cón tác dụng...Em muốn sửa thì giá khoảng bao nhiêu, thay cả màn hình hay sao?Rất mong được giải đáp, cám ơn An h/Chị nhiếu",
         "answer": "_",
         "relate_q_q": 0
      },
      {
         "score": 25.789433,
         "id": "1007829",
         "field_search": "question",
         "question": "xin chào các QTV cho em là máy em lenovo A6000 máy đang sài bình thường thì bị tắt nguồn và tự khởi động lại thì bị treo logo không thể vào màn  hình chính được.Vậy em phải làm sao ạ?",
         "answer": "_",
         "relate_q_q": 0
      },
      {
         "score": 25.77797,
         "id": "1000309",
         "field_search": "question",
         "question": "Màn hình em bi nhòe là bị làm sao ạ ??Em mới thay màn hình bị rơi . Mà nó bị nứt ở khu vực hôm ?? Cho em hỏi giờ thay màn hinh hay còn cách khác . Em j5 prime",
         "answer": "_",
         "relate_q_q": 0
      },
      {
         "score": 25.76806,
         "id": "997512",
         "field_search": "question",
         "question": "cho em hỏi máy samsung j5 pr của em đang chụp ảnh thì màn hình đơ và nó cứ sáng mãi như vậy, không khởi động lại đc như vậy là làm sao và cách sửa như thế nào ạ. em cảm ơn",
         "answer": "_",
         "relate_q_q": 0
      },
      {
         "score": 25.735313,
         "id": "1015264",
         "field_search": "question",
         "question": "Chào tgdd....!Em đang sử dụng máy samsung j5 prime ạ..Gần đây máy em có chút vấn đề về màn hình. Xuất hiện 1 vệt màu trên màn hình và 1 khoảng màu đen ở góc màn hình...Cho em hỏi cách khắc phục và phải làm như nào để giảm hiện tượng này ạ ???Mong sớm nhận được phản hồi của các ad !❤",
         "answer": "_",
         "relate_q_q": 0
      },
      {
         "score": 25.733032,
         "id": "931722",
         "field_search": "question",
         "question": "Laptop windows 10 của mình bị treo từ thanh taskbar trở lên (ko chọn được shortcut trên màn hình). Làm sao để khắc phục lỗi đó",
         "answer": "_",
         "relate_q_q": 0
      },
      {
         "score": 25.730034,
         "id": "771068",
         "field_search": "question",
         "question": "Ad ơi, cho em hỏi, em xài 6S 64GB, nhưng thỉnh thoảng máy bị chớp chớp ở phía đầu màn hình khi mở máy, từ khi up lên 9.2 thì bị thường xuyên hơn, add cho em hỏi trường hợp của em là bị lỗi gì? Em xin cám ơn.",
         "answer": "_",
         "relate_q_q": 0
      },
      {
         "score": 25.714378,
         "id": "1159718",
         "field_search": "question",
         "question": "Vui lòng hướng dẫn cho em mở khóa màn hình mà không dùng phím nguồn của máy HTC U12 life. Em cám ơn.",
         "answer": "_",
         "relate_q_q": 0
      },
      {
         "score": 25.662191,
         "id": "942987",
         "field_search": "question",
         "question": "Anh (chị) ơi em muốn thay màn hình điện thoại ip4 thường cả mặt trước với sau thì khoảng bao nhiêu tiền ạ. Em cám ơn!",
         "answer": "_",
         "relate_q_q": 0
      },
      {
         "score": 25.652128,
         "id": "771528",
         "field_search": "question",
         "question": " Màn hình máy tính em bi các đường sọc ngang nữa màn hình. Em cần làm gì để khắc phục em cảm ơn?  ",
         "answer": "_",
         "relate_q_q": 0
      },
      {
         "score": 25.63705,
         "id": "1134349",
         "field_search": "question",
         "question": "QTV cho e hỏi làm s để làm mất mấy dấu  trên màn hình điện thoại samsung j7 plus ạ. Cám ơn. ",
         "answer": "_",
         "relate_q_q": 0
      }
   ]
}