{
   "id_query": "769144",
   "total": 30392,
   "total_current": 100,
   "max_score": 91.82411,
   "origin_question": " E mới mua Oppo Neo 5, mà ko hiểu vì sao khi cài bất kì hình nào đặt làm hình nền đều bị mờ nhòa hết ",
   "hits": [
      {
         "score": 30.05206,
         "id": "1151612",
         "field_search": "question",
         "question": "E sài đt realme c1 . Maya mua được khoảng 1 tháng... nhưng xem hình ảnh trên Facebook..hay tải ảnh về đt đều bị mờ dù k có bất kì và chạm mạnh nào",
         "answer": "_",
         "relate_q_q": 0
      },
      {
         "score": 26.763733,
         "id": "833020",
         "field_search": "question",
         "question": "Mình dùng oppo neo 5. Ko hiểu sao màu sắc trên màn hình bị nhạt đi. Kiểu như bị dảm độ tương phản vậy mà mình tìm trong cài đặt mà ko thấyví dụ nhá: bình thường giao diện youtube có màu đỏ nhưng máy mình lại màu tím. Màn hình cũng bị chói hơn trc. Ad chỉ mình cách khắc phục với",
         "answer": "_",
         "relate_q_q": 0
      },
      {
         "score": 26.523184,
         "id": "1156653",
         "field_search": "question",
         "question": "cho mình hỏi là máy cuar mình là Oppo a3s Làm sao để nền khoá màn hình hiện ạ , hiện tại nền manf hình khoá cứ bị mờ như hình , mình muốn hình hiện rõ",
         "answer": "_",
         "relate_q_q": 0
      },
      {
         "score": 25.132444,
         "id": "828429",
         "field_search": "question",
         "question": "cho e hỏi e mới cài đặt 3G trên iphone! Nhưng khi cài đặt xog thì vô facebook không được, vô bất kì trình duyệt web nào cũng k được! E thử mượn máy nhỏ em thì lại vô được! Cho e hỏi nguyên nhân vì s máy e k vào đc ạ",
         "answer": "_",
         "relate_q_q": 0
      },
      {
         "score": 24.833055,
         "id": "994839",
         "field_search": "question",
         "question": "Hệ thống ơi , sao bên mình mới mua 1 iphone7plus 128gb về sử dụng chưa được một tháng , chưa rớt lần nào . Mà sao giờ loa khi có bất kì âm thanh nào phát ra từ điện thoại nó đều bị rè . Là sao ạ .",
         "answer": "_",
         "relate_q_q": 0
      },
      {
         "score": 24.613356,
         "id": "1166172",
         "field_search": "question",
         "question": "Cho e hỏi tại sao chiếc iphone xr của khi e đặ lại cài đặt vào phần hình nền lại ko có live photo ạ",
         "answer": "_",
         "relate_q_q": 0
      },
      {
         "score": 24.480333,
         "id": "1000358",
         "field_search": "question",
         "question": " Máy e từ lúc mua e vẫn cài đặt đc hình nền . nhưg bây giờ nó hiện như vậy phải làm sao . e cũq bị mấy chủ đề luôn .   ",
         "answer": "_",
         "relate_q_q": 0
      },
      {
         "score": 24.293472,
         "id": "1024456",
         "field_search": "question",
         "question": "ad ơi, làm thế nào để bỏ cái phần mờ mờ này đi ạ? e thấy hồi trước em để nền trắng vẫn đc, sau đấy e đổi nền khác xong đặt lại nền trắng nó bị thế này:(( ad giúp e với",
         "answer": "_",
         "relate_q_q": 0
      },
      {
         "score": 23.774858,
         "id": "1154004",
         "field_search": "question",
         "question": "Cách  cài đặt hình nền màn hình khóa lg l60Sao cài đặt mà chỉ hiển thị nữa bên màn hình đt thoi",
         "answer": "_",
         "relate_q_q": 0
      },
      {
         "score": 23.72885,
         "id": "1140487",
         "field_search": "question",
         "question": "E xài oppo A3s e muốn hỏi làm sao để chỉnh độ sáng màn hình lâu , nó chỉ sáng 15s mỗi lần e đều chỉnh 1' nhưng khi màn hình tắt thì cài đặt trở về 15s có cách nào chỉnh mặc định kh ạ",
         "answer": "_",
         "relate_q_q": 0
      },
      {
         "score": 23.439857,
         "id": "906868",
         "field_search": "question",
         "question": "Facebook em bị như thế này là thế nào ạ. Các thông tin đều bị mất hết id và pass cũng bị thay đổi bây giờ làm thế nào mới khôi phục lại tài khoản trong khi em cài phê duyệt đăng nhập mà không hiểu vì sao vẫn bị hách như thế này các sdt gmail khôi phục cũng bị xoá hết mong có được sự trợ giúp. Cám ơn",
         "answer": "_",
         "relate_q_q": 0
      },
      {
         "score": 22.811064,
         "id": "1016576",
         "field_search": "question",
         "question": "Mình mới mua 1 chiếc điện thoại J7 Prime cách đây 2 tháng tại TGDĐ. Dạo gần đây điện thoại hay bị lỗi khóa màn hình rồi tự sáng màn hình lại. Phải reset lại máy mới hết. Hiện tượng này ngày càng thường xuyên hơn. Mình không cài bất cứ app hình nền hay phím tắt khóa màn hình nào. Khắc phục lỗi này thế nào ạ ?",
         "answer": "_",
         "relate_q_q": 0
      },
      {
         "score": 22.709373,
         "id": "806841",
         "field_search": "question",
         "question": " Mình muốn hỏi đặt hình nền cho cuộc gọi đến và đi của máy iphone 5 thì làm thế nào? ",
         "answer": "_",
         "relate_q_q": 0
      },
      {
         "score": 22.674736,
         "id": "1016992",
         "field_search": "question",
         "question": "HTV cho e hỏi. E dùng máy glx j5. Trc vẫn cài đặt hình nền bằng ảnh trong bộ sưu tập bình thường. Nhưng sau khi cập nhật nâng cấp máy thì cài đặt hình nền bằng ảnh trong bộ sưu tập thì có bị như ảnh. Em vào cài đặt bật tắt thử mãi mà k được. Mong được giải đáp sớm ạ",
         "answer": "_",
         "relate_q_q": 0
      },
      {
         "score": 22.555267,
         "id": "1166668",
         "field_search": "question",
         "question": "Mấy oppo e mới mua khoãng 2 thang máy hết pin tắt nguồn rồi cắm xạc khoang 7 8 tiếng rút ra mở nguồn thì nó bị nhòa màn hình cảm ứng không bấm ko dc nữa . Máy e còn trong thời gian bảo hành . Trung tâm se giải quyết như thế nào",
         "answer": "_",
         "relate_q_q": 0
      },
      {
         "score": 22.345512,
         "id": "936321",
         "field_search": "question",
         "question": "cho mình hỏi. Mình mới mua Iphone 7. Chưa sử dụng lần nào. Mới chỉ cài đặt xong, tuy nhiên do quên mật khẩu khi cài đặt nên bị khóa màn hình. Xin hỏi làm cách nào để mở khóa màn hình? Xin cảm ơn.",
         "answer": "_",
         "relate_q_q": 0
      },
      {
         "score": 21.943394,
         "id": "921956",
         "field_search": "question",
         "question": "Cho em hỏi là tại sao window 10 của em không hiển thị hình nền màn hình khóa, khi nhập pass thì vẫn có hình nền trong khi em đã cài hình nền ở Setting rồi.Như hình ạ?",
         "answer": "_",
         "relate_q_q": 0
      },
      {
         "score": 21.835905,
         "id": "809071",
         "field_search": "question",
         "question": " Tại sao cài đặt hình nền live lại không được ạk. Trên iphone 6s ",
         "answer": "_",
         "relate_q_q": 0
      },
      {
         "score": 21.724215,
         "id": "782625",
         "field_search": "question",
         "question": "Mình đang dùng IPhone 5. Khi khóa màn hình. bật nút nguồn lên thì màn hình chỉ sáng mờ mờ đen, ko hiển thị ra giao diện chính của máy là sao. Mặc dù gọi đến hay nhắn tin đều nghe được chuông, Và lưu chụp màn hình thì vẫn đc. Lâu lâu những lúc khóa màn hình thì bị",
         "answer": "_",
         "relate_q_q": 0
      },
      {
         "score": 21.666092,
         "id": "996849",
         "field_search": "question",
         "question": "oppo neo 5 của em dạo này nó cứ hay bị tình trạng đứng máy bấm nút nguồn mà k sáng màn hình lên khi màn hình lên r thì lại k ăn cảm ứng bây giờ em phải làm s",
         "answer": "_",
         "relate_q_q": 0
      },
      {
         "score": 21.653528,
         "id": "1166495",
         "field_search": "question",
         "question": "Ad cho e hỏi màn hình điện thoại oppo f5 của e bị mờ với chạy sọc màu là bị làm sao ạ",
         "answer": "_",
         "relate_q_q": 0
      },
      {
         "score": 21.611195,
         "id": "785765",
         "field_search": "question",
         "question": "Máy iphone 6s mới mua bị rè loa với hay lỗi pin vs khoá màn hình có được đổi mới không? Và đổi ở bất kì thế giới di động nào cũng được phải không ạ",
         "answer": "_",
         "relate_q_q": 0
      },
      {
         "score": 21.491348,
         "id": "1134791",
         "field_search": "question",
         "question": "Mình có chiếc đt OPPO NEO 5 bị sọc dọc màn hình 1 thời gian bây giờ đã đen luôn nửa màn hình, làm sao để khắc phục ạ, Cảm ơn!",
         "answer": "_",
         "relate_q_q": 0
      },
      {
         "score": 21.345333,
         "id": "1013492",
         "field_search": "question",
         "question": "Em tắt thư viện iCloud và mất hết ảnh em phải làm sao để lấy lại đc ạ vì em thấy hình như việc bật thư viện ảnh iCloud sẽ làm ảnh bị mờ khi không có wifi",
         "answer": "_",
         "relate_q_q": 0
      },
      {
         "score": 21.321331,
         "id": "1011001",
         "field_search": "question",
         "question": "Sao màn hình của e bị mờ khi cắm sạc vào. Nhưng được một tí thì hết . Em xài dt sony xa",
         "answer": "_",
         "relate_q_q": 0
      },
      {
         "score": 21.289604,
         "id": "994090",
         "field_search": "question",
         "question": "Cho em hỏi, bây giờ em có thẻ thành viên VIP được giảm gía bất kì sản phẩm nào khi mua ở TGDĐ hay sao ạ. % ra sau và khi nào hết hạng ạ",
         "answer": "_",
         "relate_q_q": 0
      },
      {
         "score": 21.088627,
         "id": "1161777",
         "field_search": "question",
         "question": "Cho mình hỏi tại sao máy vivoy91c cài hình nền khóa màn hình không được, chỉ khi khởi động lại mới đổi được là sao",
         "answer": "_",
         "relate_q_q": 0
      },
      {
         "score": 21.068417,
         "id": "753838",
         "field_search": "question",
         "question": " Oppo Neo 7 khôi phục cài đặt gốc lại nhạc chuông hệ thống mất hết vậy? ",
         "answer": "_",
         "relate_q_q": 0
      },
      {
         "score": 20.982912,
         "id": "896015",
         "field_search": "question",
         "question": "Anh chị cho em hỏi là em mua con ip5s đc 5 tháng rồi mà ko hiểu vì sao máy em k tắt nguồn đc . Ấn nút tắt ngồn độc bị tắt màn hình thôi . Các a các chị chỉ em với",
         "answer": "_",
         "relate_q_q": 0
      },
      {
         "score": 20.6841,
         "id": "1003238",
         "field_search": "question",
         "question": "cho hỏi cái cài hình nền động bằng video tren oppo a37",
         "answer": "_",
         "relate_q_q": 0
      },
      {
         "score": 20.643482,
         "id": "791951",
         "field_search": "question",
         "question": " Hướng dẫn cách đặt tên trên màng hình khóa oppo neo 7 như thế nào ạ? ",
         "answer": "_",
         "relate_q_q": 0
      },
      {
         "score": 20.528286,
         "id": "1007227",
         "field_search": "question",
         "question": "Làm thế nào để lấy máy ảnh của oppo a37 ra hình nền hiển thị ?",
         "answer": "_",
         "relate_q_q": 0
      },
      {
         "score": 20.51524,
         "id": "1010675",
         "field_search": "question",
         "question": " A ơi cho e hỏi tại sao vào cài đặt hình nền nó lai hien thi như z koa cách nao khác phuc",
         "answer": "_",
         "relate_q_q": 0
      },
      {
         "score": 20.480795,
         "id": "881561",
         "field_search": "question",
         "question": " Tại sao iPhone 4s của em mới mua đây mà không đổi hình nền được vậy ạ ?? ",
         "answer": "_",
         "relate_q_q": 0
      },
      {
         "score": 20.374542,
         "id": "1014628",
         "field_search": "question",
         "question": "Sao điện thoại y7 prime cứ tự động tắt màn hình sau 30 giây vậy ạ, em vô chỉnh lại thì thấy chỗ không có chỗ nào chỉnh? Chỗ \"ngủ\" màn hình ở phần hiển thị trong cài đặt bị làm mờ mất",
         "answer": "_",
         "relate_q_q": 0
      },
      {
         "score": 20.196777,
         "id": "750351",
         "field_search": "question",
         "question": " Muốn cài đặt định vị trên oppo mirror 5 làm Sao? ",
         "answer": "_",
         "relate_q_q": 0
      },
      {
         "score": 20.148945,
         "id": "790367",
         "field_search": "question",
         "question": " Cách đặt tên người dùng trên màn hình khóa oppo neo 7? ",
         "answer": "_",
         "relate_q_q": 0
      },
      {
         "score": 20.135395,
         "id": "873174",
         "field_search": "question",
         "question": "Cho em hỏi làm thế nào nhắn tin sms messenger miễn phí mà em k bít cài đặt như thế nào để nhắn tin miễn phí ở oppo neo 3",
         "answer": "_",
         "relate_q_q": 0
      },
      {
         "score": 20.126383,
         "id": "744413",
         "field_search": "question",
         "question": " Cài đặt nhạc chuông tự chọn cho oppo neo 7 như thế nào ạ? ",
         "answer": "_",
         "relate_q_q": 0
      },
      {
         "score": 20.023561,
         "id": "1152334",
         "field_search": "question",
         "question": "mk mới mua oppo a3s mà sao chụp ảnh mờ quá k được nét,cứ bị xanh xanh.trong khi để chế độ chụp ảnh gốc",
         "answer": "_",
         "relate_q_q": 0
      },
      {
         "score": 20.002329,
         "id": "882843",
         "field_search": "question",
         "question": "Cho e hỏi. Ảnh đã tải lên ko hiển thị hết ảnh. Mà e vào phần alb tải lên từ di động thì vẫn hiện. E ko hiểu fb e bị làm sao nữa. Có cách nào giúp e ko 😭",
         "answer": "_",
         "relate_q_q": 0
      },
      {
         "score": 19.888796,
         "id": "1018046",
         "field_search": "question",
         "question": "đt oppo neo 7 của em bị sọc màn hình  e muốn đổi sang đt neo 9 phải bù bnhiu ak",
         "answer": "_",
         "relate_q_q": 0
      },
      {
         "score": 19.830845,
         "id": "1155759",
         "field_search": "question",
         "question": "mình mua dt j6 khi mở màn hình thì bị mờ ùi sáng lên là bị sao z",
         "answer": "_",
         "relate_q_q": 0
      },
      {
         "score": 19.821058,
         "id": "997142",
         "field_search": "question",
         "question": "Màn hình oppo neo 5 phần dưới thanh thông báo thì đục còn phần thanh thông báo thì trong .cho e hỏi nguyên nhân tai sao nó lại bị như zay",
         "answer": "_",
         "relate_q_q": 0
      },
      {
         "score": 19.816946,
         "id": "1000097",
         "field_search": "question",
         "question": "tôi dùng oppo a37. tôi bị mất biểu tượng điện thoại và tin nhắn. tôi vào cài đặt- cài đặt bổ sung- quản lý ứng dụng- phần tất cả vẫn còn 2 biểu tượng này nhưng khi nhấp vào thì ko có chữ bật lại mà có chữ buộc dừng và tắt( tắt chử ẩn mờ) làm sao để tôi lấy lai 2 bieu tượng này ra màn hình để sử dụng",
         "answer": "_",
         "relate_q_q": 0
      },
      {
         "score": 19.812092,
         "id": "831421",
         "field_search": "question",
         "question": "iPhone 5 của em chiều nay đang dùng, không cắm sạc mà tự dưng bị giật màn hình, 1 lúc n hết thì màn hình mờ đi và font chữ tự dưng nhỏ đi",
         "answer": "_",
         "relate_q_q": 0
      },
      {
         "score": 19.799433,
         "id": "1003322",
         "field_search": "question",
         "question": "e xài oppo mà e k làm rớt hay hư gì tự nhiên bị sọc màn hình cỡ 2 tuần sau thì màn hình của e bị đen luôn, e vẫn nhận dc thông báo khi ai gọi nhưng e k coi được vì màn hình chỉ màu đen thôi",
         "answer": "_",
         "relate_q_q": 0
      },
      {
         "score": 19.775259,
         "id": "1155728",
         "field_search": "question",
         "question": "2 máy của em có chung tài khoản fb mới đây em nhắn tin qua lại trên massenger lúc hai máy đều hoạt động lên mạng 3g mạnh cùng một lúc khi người khác gửi hình trên messenger thì hình ảnh 2 máy nhận dc đều bị ảnh hưởng, một máy thì hình ảnh bị bể nét, máy còn lại bị bể nét nhiều hơn mặc dù hình ảnh của người gửi cho mình không bị mờ. Ko biết có bị lỗi tài khoản hay ứng dụng gì ko mà gỡ ứng dụng rồi cài lại vẫn như vậy",
         "answer": "_",
         "relate_q_q": 0
      },
      {
         "score": 19.688324,
         "id": "876900",
         "field_search": "question",
         "question": "cho e hỏi là khi e bật voiceover của iphone 5 lên mà màn hình bị tối đen không hiện lên thì phải làm sao ạ. chụp ảnh màn hình vẫn kêu. người gọi đến nhạc chuông vẫn có nhưng tại sao màn hình lại không sáng. mà từ khi e bật voiceover lên thì màn hình mới thế ạ. xin cho e  biết là tại sao lại như vậy và cách khắc phục như thế nào ạ.",
         "answer": "_",
         "relate_q_q": 0
      },
      {
         "score": 19.647545,
         "id": "999710",
         "field_search": "question",
         "question": "Cho em hỏi đt em là j7 prime mới mua đc 5 tháng mà sao vào mấy cái ứng dụng nó bắt cài đặt lớp phủ màn hình là sao. Rùi còn ảnh thì nó tự lưu luôn ko bít sao",
         "answer": "_",
         "relate_q_q": 0
      },
      {
         "score": 19.642986,
         "id": "786370",
         "field_search": "question",
         "question": " Cho hỏi cách cài đặt hình nền themes cho Samsung galaxy j2 với ạ ",
         "answer": "_",
         "relate_q_q": 0
      },
      {
         "score": 19.612064,
         "id": "1011607",
         "field_search": "question",
         "question": "Máy LG X Power cua em kì cài đặt ứng dụng thì nó ko hiện mà phải tắt nguồn thì nó mới hiện",
         "answer": "_",
         "relate_q_q": 0
      },
      {
         "score": 19.580456,
         "id": "1013636",
         "field_search": "question",
         "question": "cho e hỏi máy wikogetway bị đơ làm sao hết đơ. em mới thay màn hình ",
         "answer": "_",
         "relate_q_q": 0
      },
      {
         "score": 19.579834,
         "id": "744747",
         "field_search": "question",
         "question": " QTV ơi cho e cách làm hình nền thay đổi 10s một hình trên win 10 được ko z???? ",
         "answer": "_",
         "relate_q_q": 0
      },
      {
         "score": 19.576523,
         "id": "999886",
         "field_search": "question",
         "question": " h e đang cài app này mà muốn đặt khoá màn hình như ảnh thì phải làm sao ạ   ",
         "answer": "_",
         "relate_q_q": 0
      },
      {
         "score": 19.575472,
         "id": "1150765",
         "field_search": "question",
         "question": "Tại sao máy (oppo A3s) của tôi mới cập nhật phần mềm buổi tối sáng kiểm tra máy lại thấy hình màn hỉnh khóa bị mờ thì phải làm sao?",
         "answer": "_",
         "relate_q_q": 0
      },
      {
         "score": 19.544455,
         "id": "1150436",
         "field_search": "question",
         "question": "Bi lỗi như hình. Khi bấm vào cài đặt   màn hình. A8 star. Máy cũ mới mua hom 1622019 ",
         "answer": "_",
         "relate_q_q": 0
      },
      {
         "score": 19.530111,
         "id": "1007804",
         "field_search": "question",
         "question": "tại sao oppo f3 e mới mua chưa đc 1 tháng mà đơ màn hình rồi,",
         "answer": "_",
         "relate_q_q": 0
      },
      {
         "score": 19.508621,
         "id": "1146561",
         "field_search": "question",
         "question": "Sao máy samsung galaxy j6 của tôi sạc chậm quá vậy 5 , 10 phút mới được 1% , máy k để màn hình sáng wifi và dữ liệu đều tắt hết . K cài ứng dụng hỗ trợ gì",
         "answer": "_",
         "relate_q_q": 0
      },
      {
         "score": 19.380241,
         "id": "1142292",
         "field_search": "question",
         "question": "Cho em hỏi ạ.  Tắt cái hình tròn trắng kia đi làm như thế nào ạ.  E dùng oppo neo 9 ạ.   ",
         "answer": "_",
         "relate_q_q": 0
      },
      {
         "score": 19.379156,
         "id": "755309",
         "field_search": "question",
         "question": "Anh chị nào biết cho e hỏi hiện e đang dùng iphone4 chạy 7.1.2 mà e vào cái ảnh cho các cuộc gọi mà anh rất nhỏ ko full màn hình nền vậy anh chị nào biết làm thế nào để cho nó full toàn màn hình e cảm ơn",
         "answer": "_",
         "relate_q_q": 0
      },
      {
         "score": 19.33413,
         "id": "1000761",
         "field_search": "question",
         "question": "E đang dùng ss a5 2017 chưa được 2 tháng hk hiểu sao cam trước bị vàng mà mờ nữa ad",
         "answer": "_",
         "relate_q_q": 0
      },
      {
         "score": 19.298115,
         "id": "1134146",
         "field_search": "question",
         "question": "em mới mua xiaomi reb mi note 5 pro mà mở ra toàn Tiếng Trung làm sao để cài đặt lại vậy ạ? ",
         "answer": "_",
         "relate_q_q": 0
      },
      {
         "score": 19.29498,
         "id": "834641",
         "field_search": "question",
         "question": " Ad ơi làm sao tải ảnh động,, lấy ảnh động làm màn hình cho Oppo neo 7 được ",
         "answer": "_",
         "relate_q_q": 0
      },
      {
         "score": 19.12265,
         "id": "1166197",
         "field_search": "question",
         "question": "Cửa hàng còn oppo neo 5 cũ ko ...................,  .......      ",
         "answer": "_",
         "relate_q_q": 0
      },
      {
         "score": 19.112545,
         "id": "998788",
         "field_search": "question",
         "question": "Cho e hỏi e mới mua dt trả góp hôm qua. Trong 30 ngày nếu e muốn đổi thì e fai lạ cửa hàng đó hay bất kì cửa hàng nào cũng dc?",
         "answer": "_",
         "relate_q_q": 0
      },
      {
         "score": 19.105087,
         "id": "764606",
         "field_search": "question",
         "question": " Oppo Neo 7 chơi được Asphalt 8 không ạ. Nếu được thì cài đặt thế nào vậy? ",
         "answer": "_",
         "relate_q_q": 0
      },
      {
         "score": 19.087341,
         "id": "1168777",
         "field_search": "question",
         "question": "Cho em hỏi là sao j4 core k cài  hình nền và  hình khóa khác nhau được ạ có cách nào k ạ",
         "answer": "_",
         "relate_q_q": 0
      },
      {
         "score": 19.052826,
         "id": "841103",
         "field_search": "question",
         "question": " em mới mua iphone 5 mà giờ sim ghép e bị khóa giờ phải làm sao? ",
         "answer": "_",
         "relate_q_q": 0
      },
      {
         "score": 19.010187,
         "id": "804614",
         "field_search": "question",
         "question": " Làm thế nào để cài mật khẩu ứng dụng trên oppo neo 7 ",
         "answer": "_",
         "relate_q_q": 0
      },
      {
         "score": 19.000837,
         "id": "1166906",
         "field_search": "question",
         "question": "Mình muốn cài đặt tạp chí màn hình khóa thì làm sao ạ, mình sử dụng Oppo f9",
         "answer": "_",
         "relate_q_q": 0
      },
      {
         "score": 18.8978,
         "id": "1152573",
         "field_search": "question",
         "question": "mình dùng điện thoại samsung j3pro. tại sao khi tắt màn hình xong khoảng vào giây sau điện thoại tự động sáng màn hình nền và màn hình khóa. cho mình hỏi là vì sao và cách khắc phục như thế nào?",
         "answer": "_",
         "relate_q_q": 0
      },
      {
         "score": 18.888489,
         "id": "788037",
         "field_search": "question",
         "question": "QTV cho em hỏi giấy bảo hành miến dán màn hình laptop của em bị mờ chữ hết giờ em muốn đi dán lại màn hình phải làm như thế nào",
         "answer": "_",
         "relate_q_q": 0
      },
      {
         "score": 18.82812,
         "id": "1141188",
         "field_search": "question",
         "question": "E đang sd mây coolpad e561. E cài đặt mật khẩu màn hình nhưng giờ e ko nhớ mk. V giờ muốn mở khoá màn hình thì phải làm sao ạ",
         "answer": "_",
         "relate_q_q": 0
      },
      {
         "score": 18.797892,
         "id": "1139693",
         "field_search": "question",
         "question": "Cho em hỏi e dùng ip xsmax, khi xem ảnh trên fb ấn vào hình ảnh đều bị mờ, thoát ảnh đó ra vào xem lại thì mới nét. Mong add hướng dẫn cách khắc phục ạ. Thanks add",
         "answer": "_",
         "relate_q_q": 0
      },
      {
         "score": 18.750973,
         "id": "838795",
         "field_search": "question",
         "question": " Cho em hỏi làm cách nào để lấy mã pin của oppo neo 5? ",
         "answer": "_",
         "relate_q_q": 0
      },
      {
         "score": 18.745663,
         "id": "1009158",
         "field_search": "question",
         "question": "Cho e hỏi oppo neo 7 tgdđ còn kinh doanh ko ạk....còn oppo neo 9 nữa ạk.....e ko pk mua máy nào nên nhờ tgdđ tư vấn trc......r e xuống xem hàng",
         "answer": "_",
         "relate_q_q": 0
      },
      {
         "score": 18.731228,
         "id": "1004916",
         "field_search": "question",
         "question": " Máy em bị như vậy thì phải làm saoem khôi phục cài đặt gốc rồi mà vẫn ko hết  ",
         "answer": "_",
         "relate_q_q": 0
      },
      {
         "score": 18.662012,
         "id": "824282",
         "field_search": "question",
         "question": "Vì sao máy tôi mỗi khi muốn xem video thì đều ko xem được và đều hiện ra chữ như trên ảnh, giờ phải làm thế nào để xem được video",
         "answer": "_",
         "relate_q_q": 0
      },
      {
         "score": 18.66006,
         "id": "1166832",
         "field_search": "question",
         "question": "Em mới mua samsung a50 mà cài đặt đợi hơn 5 phút chưa thấy vô là sao ạ",
         "answer": "_",
         "relate_q_q": 0
      },
      {
         "score": 18.658886,
         "id": "808148",
         "field_search": "question",
         "question": " Tải hình từ ZaLO về máy Oppo neo 7 mà không thấy trong thư viện là sao? ",
         "answer": "_",
         "relate_q_q": 0
      },
      {
         "score": 18.63748,
         "id": "1159370",
         "field_search": "question",
         "question": "(tôi dùng samsung J4 core) mua ở của hàng của TGDĐ hàng mới 100%. xin hỏi khi máy ở chế độ tắt màn hình cuộc gọi zalo va tin nhắn đều không nhận đươc phải khi mở ứng dụng zalo lên thi mới nhận được tn và cuộc gọi. ( tôi đã vào mục cài đặt kiểm tra ứng dụng của zalo xem có bị giới hạn thông báo hay ko) tắt màn hình đi khoảng 5p là vô hiệu lực. chỉ có zalo với viber là bị như vậy. tôi thấy rất bất tiện và ko hài lòng chút nào.. xin chỉ cách khắc phục. cảm ơn",
         "answer": "_",
         "relate_q_q": 0
      },
      {
         "score": 18.618301,
         "id": "1159942",
         "field_search": "question",
         "question": "Làm sao để hiện thị màn hình khoá k bị che mờ ạ?............................. ",
         "answer": "_",
         "relate_q_q": 0
      },
      {
         "score": 18.612902,
         "id": "1016642",
         "field_search": "question",
         "question": "đt e oppo neo 3 sạc pin đầy nhưng mở nguồn k lên,chỉ nổi lên chữ oppo mà thôi k lên hình",
         "answer": "_",
         "relate_q_q": 0
      },
      {
         "score": 18.534218,
         "id": "1166118",
         "field_search": "question",
         "question": "Cho e hỏi e muốn tải hình nền cho realme C1 mà ko biết kích thước bao nhiêu vậy ạ? Cho e kích thước ảnh nền của Realme C1 với",
         "answer": "_",
         "relate_q_q": 0
      },
      {
         "score": 18.491812,
         "id": "996761",
         "field_search": "question",
         "question": "xin chào admin,điện thoại mình là SS galaxyJ5 2016, mình mua tại TGDĐ, bị vào nước, màn hình xuất hiện đường sọc và bị mờ. Xin hỏi nếu mình đêm đến của hàng TGDĐ bất kỳ đều được hỗ trợ đúng ko ạ? và chi phí là bao nhiêu ạ. Xin cảm ơn",
         "answer": "_",
         "relate_q_q": 0
      },
      {
         "score": 18.462967,
         "id": "1136636",
         "field_search": "question",
         "question": "Cho em hỏi, sự cố này là sao vậy ạ? sao e tải bất cứ ứng dụng nào cũng đều gặp thế này. e làm mọi cách mà vẫn ko khắc phục được. e thậm chí là đã khởi động lại máy mà vẫn ko đc. e dùng Nokia lumia 530.. giúp e với!!",
         "answer": "_",
         "relate_q_q": 0
      },
      {
         "score": 18.448526,
         "id": "833150",
         "field_search": "question",
         "question": "Tôi mới mua máy Samsung J5 2016, nhưng camera sau chụp hình hay bị mờ (hình chụp xong xem lại còn mờ hơn camera trước) có phải máy bị lỗi gì k ?",
         "answer": "_",
         "relate_q_q": 0
      },
      {
         "score": 18.444443,
         "id": "1013668",
         "field_search": "question",
         "question": "Dạ cho mình hỏi làm sao để cài đặt màn hình khóa của ss j3 như lúc mới mua ạ. Cảm ơn ạ",
         "answer": "_",
         "relate_q_q": 0
      },
      {
         "score": 18.42128,
         "id": "818544",
         "field_search": "question",
         "question": " Cho e hỏi tại sao ip6 của e cài đặt ảnh người gọi mà nó k hiển lên màng hình khi có cuộc gọi ạ? ",
         "answer": "_",
         "relate_q_q": 0
      },
      {
         "score": 18.411268,
         "id": "1136130",
         "field_search": "question",
         "question": "E có đth Huawei Y9 2019 khi chụp hình xong có khi hình ko xuất hiện ở bộ sưu tập mà phải vào trong tập tin mới có. Làm cách nào để khắc phục ạ!",
         "answer": "_",
         "relate_q_q": 0
      },
      {
         "score": 18.346302,
         "id": "1002633",
         "field_search": "question",
         "question": " Ad cho e hỏiE đã sao lưu trc khi khôi phục cài đặt thế nào lấy lại đc hình ảnh, ứng dụng..... ",
         "answer": "_",
         "relate_q_q": 0
      },
      {
         "score": 18.322653,
         "id": "1164904",
         "field_search": "question",
         "question": "Em đang sài cái Huawei Y7pro 2019 màn hình mở khóa tự động đổi hình cho đến khi em cài ảnh nền thì ko đổi tự động nữa, nay em muốn đặt lại kiểu tự chuyển hình ấy, chỉ giúp em đường link để cài đặt lại ạ, em có nhờ 1 lần rồi nhưng em đã quên lối vào cài đặt, mấy anh kỹ thuật giúp em với . Thanks 😍😍😍",
         "answer": "_",
         "relate_q_q": 0
      },
      {
         "score": 18.27488,
         "id": "1145706",
         "field_search": "question",
         "question": "Xin hướng dẫn giúp tôi khắc phục lỗi này: gần đây tôi mới mua điện thoại huawei nova 3e từ TGDĐ, đt thường tự bật sáng màn hình khi đang khóa máy để nằm yên, và cả khi đang sạc pin đều bị hiện tượng giống nhau; màn hình khóa tối tự nhiên bật lên hình nền màn hình chính (chỉ hình nền, và thanh thông tin trên cùng thôi, trên màn hình chỉ hiện hình nền không kèm thông tin gì khác), sau đó nó lại tự chuyển sang màn hình khóa (có đồng hồ, ngày, ...) rồi tắt tối lại. Cứ khoảng 10' lại bị vậy. Xin hướng dẫn tôi khắc phục lỗi này. Xin cảm ơn!",
         "answer": "_",
         "relate_q_q": 0
      },
      {
         "score": 18.27108,
         "id": "1138179",
         "field_search": "question",
         "question": "Màn hình đt samsung j3 pro tự nhiên bị mờ như này là bị làm sao ạ",
         "answer": "_",
         "relate_q_q": 0
      },
      {
         "score": 18.262487,
         "id": "1022519",
         "field_search": "question",
         "question": "Cho chị hỏi. Xóa zalo trên dt khi cài đặt lại mất hết hình và tin nhắn. Vạy có cách nào khôi phục lại bản gốc ko. Chị cảm ơn nh.",
         "answer": "_",
         "relate_q_q": 0
      },
      {
         "score": 18.239483,
         "id": "1005948",
         "field_search": "question",
         "question": "có cách nào làm cho ứng dụng trong suốt thấy được ảnh nền ko hình như em có xem qua mẹo hay TGDĐ mà quên rồi ",
         "answer": "_",
         "relate_q_q": 0
      },
      {
         "score": 18.234735,
         "id": "1158470",
         "field_search": "question",
         "question": "Điện thoại Oppo F9 mới mua mà sao em bị gặp trường hợp sóng điện thoại ổn định, mạng tốt nhưng khi gọi điện, bất kể là gọi thường, gọi messenger hay Zalo đều bị đầu dây bên kia phản ánh là nghe rất ồn, tạp âm trong khi đầu đấy bên em đang yên tĩnh?",
         "answer": "_",
         "relate_q_q": 0
      },
      {
         "score": 18.214764,
         "id": "1010233",
         "field_search": "question",
         "question": "Mình mới dùng Samsung j5 Prime được hơn một tháng, chả hiểu sao âm lượng thông báo cứ tự động tăng hết cỡ dù mình chả động vào điện thoại. Mình cũng không cài đặt nhiều ứng dụng. Cảm thấy rất khó chịu vì cứ phải đặt đi đặt lại.",
         "answer": "_",
         "relate_q_q": 0
      }
   ]
}